via_hub_logistc/__init__.py
via_hub_logistc/core/via_file.py
via_hub_logistc/core/via_number.py
via_hub_logistc/core/via_report.py
via_hub_logistc/core/via_scenario.py
via_hub_logistc/core/via_text.py
via_hub_logistc/core/via_timer.py
via_hub_logistc/keyword/kws_db2.py
via_hub_logistc/keyword/kws_microsoft.py
via_hub_logistc/keyword/kws_mongodb.py
via_hub_logistc/keyword/kws_text.py
via_hub_logistc/model/zephry.py
via_hub_logistc-1.0.16.dist-info/WHEEL
via_hub_logistc-1.0.16.dist-info/METADATA
via_hub_logistc-1.0.16.dist-info/RECORD
