Metadata-Version: 2.1
Name: via-hub-logistc
Version: 1.0.16
Summary: This project is intended to be a facilitator for new developments for test automation
Author: Jaderson Macedo
Author-email: jaderson.macedo@viavarejo.com.br
Requires-Python: >=3.10,<4.0
Classifier: Programming Language :: Python :: 3
Classifier: Programming Language :: Python :: 3.10
